sttable2/__init__.py
sttable2/parser.py
sttable2/table.py
sttable2-0.0.1.dist-info/LICENSE
sttable2-0.0.1.dist-info/METADATA
sttable2-0.0.1.dist-info/WHEEL
sttable2-0.0.1.dist-info/top_level.txt
sttable2-0.0.1.dist-info/RECORD
