Metadata-Version: 2.1
Name: sttable2
Version: 0.0.1
Summary: Parser of multi-lines string representation tables
Home-page: https://github.com/yaoanderson/sttable2
Author: Anderson.Yao
Author-email: 359747390@qq.com
License: MIT
Platform: UNKNOWN
Classifier: Development Status :: 3 - Alpha
Classifier: License :: OSI Approved :: MIT License
Classifier: Programming Language :: Python
Classifier: Programming Language :: Python :: 3.7
Classifier: Programming Language :: Python :: 3.8
Classifier: Topic :: Software Development :: Libraries
Classifier: Topic :: Software Development :: Libraries :: Python Modules
Classifier: Intended Audience :: Developers
Requires-Python: >=3.7
License-File: LICENSE
